{
  "date": "2026-04-06",
  "element": "Lutetium",
  "atomicNumber": 71,
  "symbol": "Lu",
  "quiz": [
    {
      "question": "What is the crustal abundance of Lutetium?",
      "options": [
        {
          "text": "5650.0 mg/kg",
          "element": "Titanium"
        },
        {
          "text": "165.0 mg/kg",
          "element": "Zirconium"
        },
        {
          "text": "0.8 mg/kg",
          "element": "Lutetium"
        },
        {
          "text": "7.05 mg/kg",
          "element": "Samarium"
        }
      ],
      "correct": "0.8 mg/kg"
    },
    {
      "question": "Who discovered Lutetium?",
      "options": [
        {
          "text": "Martin Klaproth",
          "element": "Zirconium"
        },
        {
          "text": "William Gregor",
          "element": "Titanium"
        },
        {
          "text": "Argonne, Los Alamos, U of Calif",
          "element": "Fermium"
        },
        {
          "text": "Georges Urbain",
          "element": "Lutetium"
        }
      ],
      "correct": "Georges Urbain"
    },
    {
      "question": "When was Lutetium first discovered?",
      "options": [
        {
          "text": "1953",
          "element": "Fermium"
        },
        {
          "text": "1907",
          "element": "Lutetium"
        },
        {
          "text": "1789",
          "element": "Zirconium"
        },
        {
          "text": "1791",
          "element": "Titanium"
        }
      ],
      "correct": "1907"
    },
    {
      "question": "Which countries are the top producers of Lutetium?",
      "options": [
        {
          "text": "1) China  2) Russia  3) Malaysia",
          "element": "Lutetium"
        },
        {
          "text": "1) China  2) India  3) USA",
          "element": "Sodium"
        },
        {
          "text": "1) Canada  2) Australia  3) South Africa",
          "element": "Titanium"
        },
        {
          "text": "1) Australia  2) South Africa  3) China",
          "element": "Zirconium"
        }
      ],
      "correct": "1) China  2) Russia  3) Malaysia"
    }
  ]
}
