{
  "date": "2026-03-08",
  "element": "Livermorium",
  "atomicNumber": 116,
  "symbol": "Lv",
  "quiz": [
    {
      "question": "When was Livermorium first discovered?",
      "options": [
        {
          "text": "2000",
          "element": "Livermorium"
        },
        {
          "text": "1953",
          "element": "Fermium"
        },
        {
          "text": "1766",
          "element": "Hydrogen"
        },
        {
          "text": "1830",
          "element": "Vanadium"
        }
      ],
      "correct": "2000"
    },
    {
      "question": "Who discovered Livermorium?",
      "options": [
        {
          "text": "Nils Sefstr\u00f6m",
          "element": "Vanadium"
        },
        {
          "text": "Argonne, Los Alamos, U of Calif",
          "element": "Fermium"
        },
        {
          "text": "Lawrence Livermore National Laboratory",
          "element": "Livermorium"
        },
        {
          "text": "Known to the ancients.",
          "element": "Copper"
        }
      ],
      "correct": "Lawrence Livermore National Laboratory"
    },
    {
      "question": "What is the density of Livermorium?",
      "options": [
        {
          "text": "12.9 g/cm\u00b3",
          "element": "Livermorium"
        },
        {
          "text": "9.7 g/cm\u00b3",
          "element": "Fermium"
        },
        {
          "text": "8.96 g/cm\u00b3",
          "element": "Copper"
        },
        {
          "text": "6.0 g/cm\u00b3",
          "element": "Vanadium"
        }
      ],
      "correct": "12.9 g/cm\u00b3"
    }
  ]
}
